LICENSE.txt
MANIFEST.in
README.md
setup.cfg
setup.py
auroraapi/__init__.py
auroraapi/api.py
auroraapi/audio.py
auroraapi/globals.py
auroraapi/interpret.py
auroraapi/speech.py
auroraapi/text.py
auroraapi.egg-info/PKG-INFO
auroraapi.egg-info/SOURCES.txt
auroraapi.egg-info/dependency_links.txt
auroraapi.egg-info/requires.txt
auroraapi.egg-info/top_level.txt
auroraapi/dialog/__init__.py
auroraapi/dialog/context.py
auroraapi/dialog/dialog.py
auroraapi/dialog/graph.py
auroraapi/dialog/util.py
auroraapi/dialog/step/__init__.py
auroraapi/dialog/step/listen.py
auroraapi/dialog/step/speech.py
auroraapi/dialog/step/step.py
auroraapi/dialog/step/udf.py